dbxflow/__init__.py
dbxflow-0.1.0.dist-info/WHEEL
dbxflow-0.1.0.dist-info/METADATA
dbxflow-0.1.0.dist-info/RECORD
